LICENSE
MANIFEST.in
README.md
setup.cfg
setup.py
bert_score_cli/__init__.py
bert_score_cli/score.py
bert_score_cli/visualize.py
code_bert_score/__init__.py
code_bert_score/score.py
code_bert_score/scorer.py
code_bert_score/utils.py
code_bert_score.egg-info/PKG-INFO
code_bert_score.egg-info/SOURCES.txt
code_bert_score.egg-info/dependency_links.txt
code_bert_score.egg-info/entry_points.txt
code_bert_score.egg-info/requires.txt
code_bert_score.egg-info/top_level.txt