Metadata-Version: 2.1
Name: code-bert-score
Version: 0.4.1
Summary: PyTorch implementation of Code BERT score
Home-page: https://github.com/neulab/code-bert-score
Download-URL: https://github.com/neulab/code-bert-score/archive/refs/tags/v0.4.1.tar.gz
Author: Shuyan Zhou, Uri Alon, Sumit Agarwal, and Graham Neubig
Author-email: urialon1@gmail.com
License: MIT
Keywords: BERT NLP deep learning google metric
Platform: UNKNOWN
Classifier: Intended Audience :: Science/Research
Classifier: License :: OSI Approved :: MIT License
Classifier: Programming Language :: Python :: 3
Classifier: Topic :: Scientific/Engineering :: Artificial Intelligence
Requires-Python: >=3.6
License-File: LICENSE
